clacks/__init__.py
clacks/middleware.py
django_clacks-0.3.0.dist-info/WHEEL
django_clacks-0.3.0.dist-info/METADATA
django_clacks-0.3.0.dist-info/RECORD
